dbz_lib-0.1.3.dist-info/METADATA
dbz_lib-0.1.3.dist-info/WHEEL
dbz_lib/__init__.py
dbz_lib/dbz_lib.cpython-310-darwin.so
dbz_lib-0.1.3.dist-info/RECORD
