Metadata-Version: 2.1
Name: dbz-lib
Version: 0.1.3
Summary: Library for working with the Databento Binary Encoding (DBZ) format
Keywords: market-data,json,csv,conversion,encoding
Author: Databento <support@databento.com>
Author-email: Databento <support@databento.com>
License: Apache-2.0
Project-URL: Source Code, https://github.com/databento/dbz
